{
  "lastUpdated": "2026-04-18T19:08:31.071Z",
  "rates": [
    {
      "item": "Gold Hallmark",
      "unit": "Tola",
      "rate": "299800"
    },
    {
      "item": "Gold Tajabi",
      "unit": "Tola",
      "rate": "296800"
    },
    {
      "item": "Silver",
      "unit": "Tola",
      "rate": "5130"
    },
    {
      "item": "Gold Hallmark",
      "unit": "10 gram",
      "rate": "257030"
    },
    {
      "item": "Gold Tajabi",
      "unit": "10 gram",
      "rate": "254459.7"
    },
    {
      "item": "Silver",
      "unit": "10 gram",
      "rate": "4398"
    }
  ]
}