{
  "lastUpdated": "2026-06-01T21:42:51.059Z",
  "rates": [
    {
      "item": "Gold Hallmark",
      "unit": "Tola",
      "rate": "310900"
    },
    {
      "item": "Gold Tajabi",
      "unit": "Tola",
      "rate": "307800"
    },
    {
      "item": "Silver",
      "unit": "Tola",
      "rate": "5355"
    },
    {
      "item": "Gold Hallmark",
      "unit": "10 gram",
      "rate": "266545"
    },
    {
      "item": "Gold Tajabi",
      "unit": "10 gram",
      "rate": "263879.55"
    },
    {
      "item": "Silver",
      "unit": "10 gram",
      "rate": "4591"
    }
  ]
}